geocoder/Geocoder.py
geocoder/ReverseGeocoder.py
geocoder/Tokenizer.py
geocoder/__init__.py
geocoder/tokens.py
geocoder/db/__init__.py
geocoder/db/base.py
geocoder/db/cassandradb.py
geocoder/db/dynamodb.py
geocoder/db/leveldb.py
geocoder/db/rocksdb.py
geocoder/hash/BldAddress.py
geocoder/hash/JibunAddress.py
geocoder/hash/RoadAddress.py
geocoder/hash/__init__.py
geocoder/util/BldSimplifier.py
geocoder/util/HSimplifier.py
geocoder/util/RoadSimplifier.py
geocoder/util/__init__.py
geocoder/util/hcodematcher.py
geocoder/util/pnumatcher.py
geocoder/util/roadmatcher.py
geocoder_kr/Geocoder.py
geocoder_kr/ReverseGeocoder.py
geocoder_kr/Tokenizer.py
geocoder_kr/__init__.py
geocoder_kr/geocoder.py
geocoder_kr/reverse_geocoder.py
geocoder_kr/tokens.py
geocoder_kr/db/__init__.py
geocoder_kr/db/base.py
geocoder_kr/db/cassandradb.py
geocoder_kr/db/dynamodb.py
geocoder_kr/db/leveldb.py
geocoder_kr/db/rocksdb.py
geocoder_kr/hash/BldAddress.py
geocoder_kr/hash/JibunAddress.py
geocoder_kr/hash/RoadAddress.py
geocoder_kr/hash/__init__.py
geocoder_kr/util/BldSimplifier.py
geocoder_kr/util/HSimplifier.py
geocoder_kr/util/RoadSimplifier.py
geocoder_kr/util/__init__.py
geocoder_kr/util/hcodematcher.py
geocoder_kr/util/pnumatcher.py
geocoder_kr/util/roadmatcher.py
src/__init__.py
src/api.py
src/api_fast.py
src/config.py
src/test.py
src/geocoder/Geocoder.py
src/geocoder/ReverseGeocoder.py
src/geocoder/Tokenizer.py
src/geocoder/__init__.py
src/geocoder/tokens.py
src/geocoder/db/__init__.py
src/geocoder/db/base.py
src/geocoder/db/cassandradb.py
src/geocoder/db/dynamodb.py
src/geocoder/db/leveldb.py
src/geocoder/db/rocksdb.py
src/geocoder/hash/BldAddress.py
src/geocoder/hash/JibunAddress.py
src/geocoder/hash/RoadAddress.py
src/geocoder/hash/__init__.py
src/geocoder/util/BldSimplifier.py
src/geocoder/util/HSimplifier.py
src/geocoder/util/RoadSimplifier.py
src/geocoder/util/__init__.py
src/geocoder/util/hcodematcher.py
src/geocoder/util/pnumatcher.py
src/geocoder/util/roadmatcher.py
geocoder_kr-0.28.dist-info/LICENSE
geocoder_kr-0.28.dist-info/METADATA
geocoder_kr-0.28.dist-info/WHEEL
geocoder_kr-0.28.dist-info/top_level.txt
geocoder_kr-0.28.dist-info/RECORD
