Metadata-Version: 2.1
Name: geocoder-kr
Version: 0.28
Summary: Python-based geocoding solution for Korean addresses
Home-page: https://github.com/gisman/geocoder-kr
Author: gisman
Author-email: gisman@gmail.com
License: CC-BY-NC-SA-4.0
Platform: UNKNOWN
Classifier: Programming Language :: Python :: 3
Classifier: Operating System :: POSIX :: Linux
Requires-Python: >=3.6, <3.12
License-File: LICENSE
Requires-Dist: annotated-types==0.7.0
Requires-Dist: anyio==4.7.0
Requires-Dist: attrs==24.3.0
Requires-Dist: certifi==2024.12.14
Requires-Dist: charset-normalizer==3.4.1
Requires-Dist: click-plugins==1.1.1
Requires-Dist: click==8.1.8
Requires-Dist: cligj==0.7.2
Requires-Dist: environs==11.2.1
Requires-Dist: exceptiongroup==1.2.2
Requires-Dist: fastapi==0.115.6
Requires-Dist: fiona==1.10.1
Requires-Dist: h11==0.14.0
Requires-Dist: idna==3.10
Requires-Dist: polygon-geohasher==0.0.1
Requires-Dist: pydantic==2.10.4
Requires-Dist: pydantic-core==2.27.2
Requires-Dist: pyproj==3.7.0
Requires-Dist: python-geohash==0.8.5
Requires-Dist: requests==2.32.3
Requires-Dist: rocksdb3==0.1.0
Requires-Dist: shapely==2.0.6
Requires-Dist: sniffio==1.3.1
Requires-Dist: starlette==0.41.3
Requires-Dist: twine==6.0.1
Requires-Dist: typing-extensions==4.12.2
Requires-Dist: urllib3==2.3.0
Requires-Dist: uvicorn==0.34.0
Requires-Dist: uvloop==0.21.0
